wheezy_extractor/__init__.py
wheezy_extractor-1.0.1.dist-info/LICENSE
wheezy_extractor-1.0.1.dist-info/METADATA
wheezy_extractor-1.0.1.dist-info/WHEEL
wheezy_extractor-1.0.1.dist-info/entry_points.txt
wheezy_extractor-1.0.1.dist-info/top_level.txt
wheezy_extractor-1.0.1.dist-info/RECORD
