Metadata-Version: 2.1
Name: wheezy-extractor
Version: 1.0.1
Summary: Babel extracto for Wheezy templates
Home-page: https://github.com/Polsaker/wheezy_extractor
Author: UNKNOWN
Author-email: UNKNOWN
License: UNKNOWN
Platform: UNKNOWN
Classifier: Programming Language :: Python :: 3
Classifier: License :: OSI Approved :: MIT License
Classifier: Operating System :: OS Independent
